pystream/__init__.py
pystream/pystream.py
pystream_wushilin-1.0.7.dist-info/LICENSE
pystream_wushilin-1.0.7.dist-info/METADATA
pystream_wushilin-1.0.7.dist-info/WHEEL
pystream_wushilin-1.0.7.dist-info/top_level.txt
pystream_wushilin-1.0.7.dist-info/RECORD
